{
  "bureau": "Meuble avec un plateau, utilisé pour écrire, travailler ou ranger des documents.",
  "cabinet": "Petit meuble ou pièce servant au rangement ou à un usage particulier.",
  "carreau": "Plaque mince, souvent en céramique ou en verre, utilisée pour couvrir une surface.",
  "chaise": "Siège pour une personne, généralement muni d'un dossier.",
  "classe": "Groupe d'élèves suivant un enseignement ensemble ou salle où ils travaillent.",
  "cle": "Objet servant à ouvrir ou fermer une serrure.",
  "coin": "Angle d'un lieu ou petite partie retirée d'un espace.",
  "couloir": "Passage allongé reliant différentes pièces ou zones.",
  "dossier": "Ensemble de documents réunis sur un même sujet.",
  "eau": "Liquide transparent, indispensable à la vie.",
  "ecole": "Lieu où l'on reçoit un enseignement.",
  "ecriture": "Action d'écrire ou manière de former les lettres.",
  "entree": "Action d'entrer ou passage permettant l'accès à un lieu.",
  "escalier": "Ensemble de marches permettant de monter ou descendre.",
  "etagere": "Planche fixée pour poser ou ranger des objets.",
  "etude": "Travail intellectuel destiné à apprendre ou approfondir un sujet.",
  "exterieur": "Partie de ce qui est dehors, à l'air libre.",
  "fenetre": "Ouverture pratiquée dans un mur pour laisser passer la lumière et l'air.",
  "interieur": "Partie située dedans, à l'intérieur d'un espace fermé.",
  "lavabo": "Appareil sanitaire destiné à se laver, surtout les mains et le visage.",
  "lecture": "Action de lire un texte.",
  "lit": "Meuble sur lequel on se couche pour dormir ou se reposer.",
  "marche": "Degré d'un escalier sur lequel on pose le pied.",
  "matelas": "Coussin épais sur lequel on dort, posé sur un lit.",
  "maternelle": "École destinée aux très jeunes enfants avant l'école élémentaire.",
  "meuble": "Objet servant à l'aménagement et à l'usage d'une habitation ou d'une pièce.",
  "mousse": "Matière légère et souple, ou amas de petites bulles à la surface d'un liquide.",
  "mur": "Paroi verticale d'une construction.",
  "porte": "Ouverture mobile servant à entrer ou sortir d'un lieu.",
  "portemanteau": "Support destiné à suspendre vêtements, manteaux ou accessoires.",
  "poubelle": "Récipient destiné à recevoir les déchets.",
  "radiateur": "Appareil servant à diffuser la chaleur dans une pièce.",
  "rampe": "Barre d'appui le long d'un escalier ou d'un passage incliné.",
  "recreation": "Temps de pause accordé aux élèves entre les cours.",
  "rentree": "Retour à l'école ou reprise des activités après une interruption.",
  "toilette": "Lieu ou ensemble des soins consacrés à la propreté du corps.",
  "elephant": "Grand mammifère à trompe, aux défenses souvent développées.",
  "girafe": "Mammifère africain au très long cou.",
  "football": "Sport collectif opposant deux équipes qui cherchent à marquer avec un ballon.",
  "guitare": "Instrument de musique à cordes pincées.",
  "montagne": "Grande élévation naturelle du terrain.",
  "chocolat": "Préparation alimentaire obtenue à partir du cacao.",
  "ordinateur": "Machine électronique capable de traiter des informations.",
  "plage": "Étendue de sable ou de galets au bord de la mer ou d'un lac.",
  "bibliotheque": "Lieu ou meuble où l'on conserve des livres.",
  "papillon": "Insecte ailé issu de la métamorphose d'une chenille.",
  "restaurant": "Établissement où l'on sert des repas.",
  "calendrier": "Système ou support indiquant les jours, semaines et mois de l'année.",
  "aventure": "Événement plein d'imprévu ou expérience sortant de l'ordinaire.",
  "pyramide": "Monument ou solide à base polygonale dont les faces se rejoignent en un sommet.",
  "volcan": "Relief terrestre par lequel s'échappent du magma, des gaz ou des cendres.",
  "chrysantheme": "Plante ornementale à fleurs souvent cultivée dans les jardins.",
  "xylophone": "Instrument de musique composé de lames que l'on frappe avec des maillets.",
  "psychiatre": "Médecin spécialiste des troubles mentaux.",
  "bureaucratie": "Ensemble des services administratifs ou manière lourde de gérer par l'administration.",
  "prestidigitateur": "Artiste qui réalise des tours d'illusion par adresse manuelle.",
  "vraisemblable": "Qui paraît conforme à la vérité ou crédible.",
  "anticonstitutionnel": "Contraire à la constitution d'un État.",
  "philosophie": "Discipline de réflexion portant sur la connaissance, l'existence et les valeurs.",
  "extraordinaire": "Qui sort de l'ordinaire, remarquable ou exceptionnel.",
  "perpendiculaire": "Qui forme un angle droit avec une autre ligne ou surface.",
  "circumnavigation": "Navigation autour du monde ou autour d'un territoire.",
  "kleptomanie": "Trouble poussant à voler de façon répétée et compulsive.",
  "psychanalyste": "Spécialiste pratiquant la psychanalyse.",
  "bioluminescence": "Production et émission de lumière par un organisme vivant.",
  "astrophysique": "Branche de la physique qui étudie les astres et les phénomènes de l'univers."
}
